defter/__init__.py
defter/backend/__init__.py
defter/backend/__main__.py
defter/backend/browsers.py
defter/backend/chrome.py
defter/backend/defter.js
defter/backend/edge.py
defter/backend/electron.py
defter/feature/__init__.py
defter/feature/accelerator.py
defter/feature/cli.py
defter/feature/frontendc.py
defter/feature/xpopen.py
defter/feature/demo/__init__.py
defter/feature/demo/backend.py
defter/feature/demo/frontend-demo.py
defter/feature/demo/src/__init__.py
defter/feature/demo/src/defter.js
defter/feature/demo/src/favicon.ico
defter/feature/demo/src/frontend-demo.html
defter/feature/demo/src/build/DefterVM.runtime.js
defter/feature/demo/src/build/__init__.py
defter/feature/demo/src/build/frontend-demo.js
defter/feature/new/__init__.py
defter/feature/new/backend.py
defter/feature/new/frontend.py
defter/feature/new/src/__init__.py
defter/feature/new/src/defter.js
defter/feature/new/src/favicon.ico
defter-2.0b4.dist-info/LICENSE
defter-2.0b4.dist-info/METADATA
defter-2.0b4.dist-info/WHEEL
defter-2.0b4.dist-info/entry_points.txt
defter-2.0b4.dist-info/top_level.txt
defter-2.0b4.dist-info/RECORD
